setup.py
dsnd_probability_786/Binomialdistribution.py
dsnd_probability_786/Gaussiandistribution.py
dsnd_probability_786/Generaldistribution.py
dsnd_probability_786/__init__.py
dsnd_probability_786.egg-info/PKG-INFO
dsnd_probability_786.egg-info/SOURCES.txt
dsnd_probability_786.egg-info/dependency_links.txt
dsnd_probability_786.egg-info/not-zip-safe
dsnd_probability_786.egg-info/top_level.txt