Metadata-Version: 1.0
Name: dsnd-probability-786
Version: 1.1
Summary: Gaussian and Binomial distributions
Home-page: UNKNOWN
Author: Faiza Ahmed
Author-email: syeda.faiza.ahmed@gmail.com
License: UNKNOWN
Platform: UNKNOWN
